wmb/__init__.py
wmb/_version.py
wmb/google_sheet.py
wmb/utilities.py
wmb/aibs/__init__.py
wmb/annot/__init__.py
wmb/annot/aibs.py
wmb/annot/annot.py
wmb/annot/broad.py
wmb/annot/cemba.py
wmb/annot/glia.py
wmb/annot/integration.py
wmb/brain_region/__init__.py
wmb/brain_region/ccf_ref.py
wmb/broad/__init__.py
wmb/cemba/__init__.py
wmb/cemba/_atac.py
wmb/cemba/_epi_retro.py
wmb/cemba/_mc_and_m3c.py
wmb/files/AIBS.SMART.CellMetadata.213261.csv.gz
wmb/files/AIBS.SMART.DoubletsID.txt.gz
wmb/files/AIBS.SMART.GeneMap.csv
wmb/files/AIBS.SMART.KeyCellMetadata.213261.csv.gz
wmb/files/AIBS.StructureTree.lib
wmb/files/AIBS.TENX.DoubletsID.txt.gz
wmb/files/AIBS.TENX.GeneMap.csv
wmb/files/AIBS.TENX.KeySampleMetadata.688.csv.gz
wmb/files/AIBS.TENX.KeySampleMetadata.816.csv.gz
wmb/files/AIBS.TENX.SampleMetadata.688.csv.gz
wmb/files/AIBS.TENX.SampleMetadata.816.csv.gz
wmb/files/AIBS_smart_missing_info.txt
wmb/files/AIBS_tenx_missing_info.txt
wmb/files/BICCN.BrainRegionMetadata.csv
wmb/files/BROAD.TENX.DoubletsID.txt.gz
wmb/files/BROAD.TENX.GeneMap.csv
wmb/files/BROAD.TENX.SampleMetadata.csv.gz
wmb/files/CEMBA.CellMetadata.snm3C-seq.small.csv.gz
wmb/files/CEMBA.CellMetadata.snmC-seq.small.csv.gz
wmb/files/CEMBA.Liu2021Nature.snmC.metadata.csv.gz
wmb/files/CEMBA.snATAC.ClusterDescription.tsv
wmb/files/CEMBA.snm3C.100KImputedCoolURLs.csv.gz
wmb/files/CEMBA.snm3C.100KRawCoolURLs.csv.gz
wmb/files/CEMBA.snm3C.10KImputedCoolURLs.csv.gz
wmb/files/CEMBA.snm3C.10KRawCoolURLs.csv.gz
wmb/files/CEMBA.snm3C.25KImputedCoolURLs.csv.gz
wmb/files/CEMBA.snm3C.25KRawCoolURLs.csv.gz
wmb/files/CEMBA.snm3C.ALLCPaths.csv.gz
wmb/files/CEMBA.snm3C.ContactPaths.csv.gz
wmb/files/CEMBA.snm3C.DoubletsID.txt.gz
wmb/files/CEMBA.snm3C.mCGALLCPaths.csv.gz
wmb/files/CEMBA.snmC-to-snm3C.L4RegionMap.221110.dict
wmb/files/CEMBA.snmC.ALLCPaths.csv.gz
wmb/files/CEMBA.snmC.DoubletsID.txt.gz
wmb/files/CEMBA.snmC.mCGALLCPaths.csv.gz
wmb/files/__init__.py
wmb/files/_aibs.py
wmb/files/_brain_region.py
wmb/files/_broad.py
wmb-0.1.36.dist-info/LICENSE
wmb-0.1.36.dist-info/METADATA
wmb-0.1.36.dist-info/WHEEL
wmb-0.1.36.dist-info/top_level.txt
wmb-0.1.36.dist-info/RECORD
