Metadata-Version: 2.1
Name: wmb
Version: 0.1.36
Summary: misc code for whole mouse brain analysis.
Home-page: https://github.com/lhqing/whole_mouse_brain
Author: Hanqing Liu
Author-email: hanliu@salk.edu
License: MIT
Classifier: License :: OSI Approved :: MIT License
Classifier: Programming Language :: Python :: 3
Classifier: Programming Language :: Python :: 3.8
License-File: LICENSE
Requires-Dist: numpy
Requires-Dist: pandas
Requires-Dist: xarray
Requires-Dist: seaborn
Requires-Dist: matplotlib
Requires-Dist: ALLCools
